README.md
setup.cfg
setup.py
workflowhub/__init__.py
workflowhub/utils.py
workflowhub/version.py
workflowhub.egg-info/PKG-INFO
workflowhub.egg-info/SOURCES.txt
workflowhub.egg-info/dependency_links.txt
workflowhub.egg-info/requires.txt
workflowhub.egg-info/top_level.txt
workflowhub/common/__init__.py
workflowhub/common/file.py
workflowhub/common/machine.py
workflowhub/common/task.py
workflowhub/common/workflow.py
workflowhub/generator/__init__.py
workflowhub/generator/generator.py
workflowhub/generator/workflow/__init__.py
workflowhub/generator/workflow/abstract_recipe.py
workflowhub/generator/workflow/blast_recipe.py
workflowhub/generator/workflow/bwa_recipe.py
workflowhub/generator/workflow/cycles_recipe.py
workflowhub/generator/workflow/epigenomics_recipe.py
workflowhub/generator/workflow/genome_recipe.py
workflowhub/generator/workflow/montage_recipe.py
workflowhub/generator/workflow/seismology_recipe.py
workflowhub/generator/workflow/soykb_recipe.py
workflowhub/generator/workflow/srasearch_recipe.py
workflowhub/trace/__init__.py
workflowhub/trace/schema.py
workflowhub/trace/trace.py
workflowhub/trace/trace_analyzer.py
workflowhub/trace/logs/__init__.py
workflowhub/trace/logs/abstract_logs_parser.py
workflowhub/trace/logs/makeflow.py
workflowhub/trace/logs/pegasus.py