Metadata-Version: 2.1
Name: workflowhub
Version: 0.4
Summary: Community Framework for Enabling Scientific Workflow Research and Education
Home-page: https://github.com/workflowhub/workflowhub
Author: WorkflowHub team
Author-email: support@workflowhub.org
License: GPLv3
Platform: UNKNOWN
Classifier: License :: OSI Approved :: GNU General Public License v3 (GPLv3)
Classifier: Operating System :: OS Independent
Classifier: Programming Language :: Python :: 3
Classifier: Programming Language :: Python :: 3.6
Classifier: Programming Language :: Python :: 3.7
Classifier: Programming Language :: Python :: 3.8
Classifier: Programming Language :: Python :: 3.9
Classifier: Intended Audience :: Developers
Classifier: Intended Audience :: Education
Classifier: Intended Audience :: Science/Research
Classifier: Natural Language :: English
Classifier: Topic :: Documentation :: Sphinx
Classifier: Topic :: System :: Distributed Computing
Requires-Python: >=3.6
